<?xml version="1.0" encoding="UTF-8"?>
<objects serializationModel="Studio.02.03.00">
	<object class="MixerReturn" id="{7e44e7b2-3f11-4128-adc1-6c8c72a50a69}">
		<property name="volume">
			<value>-7</value>
		</property>
		<property name="name">
			<value>Night Success</value>
		</property>
		<relationship name="effectChain">
			<destination>{88636a7a-c432-448b-b4cb-b193ec15d9a0}</destination>
		</relationship>
		<relationship name="panner">
			<destination>{54b8a72a-b1f6-4cc7-a265-9e4f4b45e0e8}</destination>
		</relationship>
		<relationship name="output">
			<destination>{5aeb9694-ebf0-4043-8346-3f95f88fd596}</destination>
		</relationship>
	</object>
	<object class="MixerBusEffectChain" id="{88636a7a-c432-448b-b4cb-b193ec15d9a0}">
		<relationship name="effects">
			<destination>{e66fc6f6-8ca6-4b20-b11e-f0b7b9efdf52}</destination>
		</relationship>
	</object>
	<object class="MixerBusPanner" id="{54b8a72a-b1f6-4cc7-a265-9e4f4b45e0e8}" />
	<object class="MixerBusFader" id="{e66fc6f6-8ca6-4b20-b11e-f0b7b9efdf52}" />
</objects>
